UART/rtl/module_bit_counter.v
module uart_bit_counter(
    input clk,
    input reset,
    input bit_enable,
    
    output reg bit_done
);

reg [2:0] bit_count;

always @(posedge clk or posedge reset)
begin
    if (reset)
    begin
        bit_count<=0;
        bit_done<=0;
    end

    else  if (bit_enable)
    begin
        if (bit_count==7)
        begin
            bit_count<=0;
            bit_done<=1;
        end

        else
        begin
            bit_count<=bit_count+1;
            bit_done<=0;
        end
    end

    else
    begin
        bit_done<=0;
    end
end
endmodule

UART/rtl/module_shift_register.v
module uart_shift_register(
    input clk,
    input reset,
    input load,
    input shift_enable,
    input [7:0] data_in,
    output wire  tx_bit
);

reg[7:0] shift_reg;

always @(posedge clk or posedge reset)
begin
    if(reset)
        shift_reg<=0;
    else if(load)
        shift_reg<=data_in;
    else if (shift_enable)
        shift_reg<=shift_reg >>1;
end

assign tx_bit = shift_reg[0];
endmodule

UART/rtl/module_baud_counter.v
module uart_baud_counter(
    input clk;
    input reset;
    input baud_enable;

    output reg baud_done;  
);

reg [12:0] count;
always @(sposedge clk or posedge reset)
begin
    if(reset)
    begin
        count<=0;
        baud_done<=0;
    end

    else if(baud_enable)
    begin
        if(count==5207)
        begin
            count<=0;
            baud_done<=1;
        end

        else
        begin
            count<=count+1;
            baud_done<=0;
        end
    end

    else
    begin
        count<=0;
        baud_done<=0;
    end
end
endmodule

UART/rtl/module_uart_fsm.v
module uart_fsm(
    input clk,
    input reset,
    input start,
    input baud_done,
    input bit_done,

    output reg baud_enable,
    output reg shift_enable,
    output reg load,
    output reg bit_enable,
    output reg [1:0] state
);

parameter IDLE= 2'b00;
parameter START=2'b01;
parameter DATA=2'b10;
parameter STOP=2'b11;

reg [1:0] next_state;

always @(posedge clk or posedge reset)
begin 
    if (reset)
        state<=IDLE;
    else
        state<=next_ state;
end 

always @(*)
begin
    baud_enable=0;
    bit_enable=0;
    shift_enable=0;
    load=0;
    next_state=state;

    case(state)
        IDLE:
        begin
            if(start)
            begin
                next_state=START;
                load=1;
            end
        end

        START:
        begin
            baud_enable=1;
            if(baud_done)
            begin
                next_state=DATA;
            end
        end

        DATA:
        begin
            baud_enable=1;
            shift_enable=baud_done;
            bit_enable=baud_done;
            if(bit_done)
            begin
                next_state=STOP;
            end
        end

        STOP:
        begin
            baud_enable=1;
            if(baud_done)
            begin
                next_state=IDLE;
            end
        end
    endcase
end
endmodule

UART/rtl/module_uart_tx.v
module uart_tx(
    input clk,
    input reset,
    input start,
    input [7:0] data_in,
    output tx
);

parameter IDLE = 2'b00;
parameter START = 2'b01;
parameter DATA = 2'b10;
parameter STOP = 2'b11;

wire [1:0] state;
wire baud_done;
wire bit_done;

wire baud_enable;
wire shift_enable;
wire load;
wire bit_enable;

wire tx_bit;

uart_fsm fsm(
    .clk(clk),
    .reset(reset),
    .state(state),
    .start(start),
    .baud_done(baud_done),
    .bit_done(bit_done),

    .baud_enable(baud_enable),
    .shift_enable(shift_enable),
    .load(load),
    .bit_enable(bit_enable)
);

uart_baud_counter baud_ctr(
    .clk(clk),
    .reset(reset),
    .baud_enable(baud_enable),
    .baud_done(baud_done)
);

uart_shift_register shift_reg(
    .clk(clk),
    .reset(reset),
    .load(load),
    .shift_enable(shift_enable),
    .data_in(data_in),
    .tx_bit(tx_bit)
);

uart_bit_counter bit_ctr(
    .clk(clk),
    .reset(reset),
    .bit_enable(bit_enable),
    .bit_done(bit_done)
);

assign tx =
    (state == IDLE)  ? 1'b1 :
    (state == START) ? 1'b0 :
    (state == DATA)  ? tx_bit :
    (state == STOP)  ? 1'b1 :
                       1'b1;
endmodule

UART/tb/uart_tx_tb.v
module uart_tx_tb;

reg clk;
reg reset;
reg start;
reg [7:0] data_in;

wire tx;


uart_tx dut(
    .clk(clk),
    .reset(reset),
    .start(start),
    .data_in(data_in),
    .tx(tx)
);



always #10 clk = ~clk;

initial
begin
    clk=0;
    reset=1;
    start=0;
    data_in=8'h00;

    #100;
    reset=0;

    #100;
    data_in=8'h41;

    start=1;
    #20;
    start=0;

    #1000000;

    $finish;
end

initial
begin   
    $dumpfiles("uart.vcd");
    $dumpvars(0,uart_tx_tb);
end
endmodule

uart.vcd
$date
	Thu Jun 11 19:48:24 2026
$end
$version
	Icarus Verilog
$end
$timescale
	1s
$end
$scope module uart_tx_tb $end
$var wire 1 ! tx $end
$var reg 1 " clk $end
$var reg 8 # data_in [7:0] $end
$var reg 1 $ reset $end
$var reg 1 % start $end
$scope module dut $end
$var wire 1 " clk $end
$var wire 8 & data_in [7:0] $end
$var wire 1 $ reset $end
$var wire 1 % start $end
$var wire 1 ' tx_bit $end
$var wire 1 ! tx $end
$var wire 2 ( state [1:0] $end
$var wire 1 ) shift_enable $end
$var wire 1 * load $end
$var wire 1 + bit_enable $end
$var wire 1 , bit_done $end
$var wire 1 - baud_enable $end
$var wire 1 . baud_done $end
$var parameter 2 / DATA $end
$var parameter 2 0 IDLE $end
$var parameter 2 1 START $end
$var parameter 2 2 STOP $end
$scope module baud_ctr $end
$var wire 1 " clk $end
$var wire 1 $ reset $end
$var wire 1 - baud_enable $end
$var reg 1 . baud_done $end
$var reg 13 3 count [12:0] $end
$upscope $end
$scope module bit_ctr $end
$var wire 1 " clk $end
$var wire 1 $ reset $end
$var wire 1 + bit_enable $end
$var reg 3 4 bit_count [2:0] $end
$var reg 1 , bit_done $end
$upscope $end
$scope module fsm $end
$var wire 1 . baud_done $end
$var wire 1 , bit_done $end
$var wire 1 " clk $end
$var wire 1 $ reset $end
$var wire 1 % start $end
$var parameter 2 5 DATA $end
$var parameter 2 6 IDLE $end
$var parameter 2 7 START $end
$var parameter 2 8 STOP $end
$var reg 1 - baud_enable $end
$var reg 1 + bit_enable $end
$var reg 1 * load $end
$var reg 2 9 next_state [1:0] $end
$var reg 1 ) shift_enable $end
$var reg 2 : state [1:0] $end
$upscope $end
$scope module shift_reg $end
$var wire 1 " clk $end
$var wire 8 ; data_in [7:0] $end
$var wire 1 * load $end
$var wire 1 $ reset $end
$var wire 1 ) shift_enable $end
$var wire 1 ' tx_bit $end
$var reg 8 < shift_reg [7:0] $end
$upscope $end
$upscope $end
$upscope $end
$enddefinitions $end
$comment Show the parameter values. $end
$dumpall
b11 8
b1 7
b0 6
b10 5
b11 2
b1 1
b0 0
b10 /
$end
#0
$dumpvars
b0 <
b0 ;
b0 :
b0 9
b0 4
b0 3
0.
0-
0,
0+
0*
0)
b0 (
0'
b0 &
0%
1$
b0 #
0"
1!
$end
#10
1"
#20
0"
#30
1"
#40
0"
#50
1"
#60
0"
#70
1"
#80
0"
#90
1"
#100
0"
0$
#110
1"
#120
0"
#130
1"
#140
0"
#150
1"
#160
0"
#170
1"
#180
0"
#190
1"
#200
1*
b1 9
0"
1%
b1000001 #
b1000001 &
b1000001 ;
#210
0!
1'
1-
0*
b1000001 <
b1 (
b1 :
1"
#220
1-
0"
0%
#230
b1 3
1"
#240
0"
#250
b10 3
1"
#260
0"
#270
b11 3
1"
#280
0"
#290
b100 3
1"
#300
0"
#310
b101 3
1"
#320
0"
#330
b110 3
1"
#340
0"
#350
b111 3
1"
#360
0"
#370
b1000 3
1"
#380
0"
#390
b1001 3
1"
#400
0"
#410
b1010 3
1"
#420
0"
#430
b10 9
1-
1.
b0 3
1"
#440
0"
#450
1!
1-
0.
b1 3
b10 (
b10 :
1"
#460
0"
#470
b10 3
1"
#480
0"
#490
b11 3
1"
#500
0"
#510
b100 3
1"
#520
0"
#530
b101 3
1"
#540
0"
#550
b110 3
1"
#560
0"
#570
b111 3
1"
#580
0"
#590
b1000 3
1"
#600
0"
#610
b1001 3
1"
#620
0"
#630
b1010 3
1"
#640
0"
#650
1+
1)
1-
1.
b0 3
1"
#660
0"
#670
0!
0)
0+
1-
0'
0.
b1 3
b100000 <
b1 4
1"
#680
0"
#690
b10 3
1"
#700
0"
#710
b11 3
1"
#720
0"
#730
b100 3
1"
#740
0"
#750
b101 3
1"
#760
0"
#770
b110 3
1"
#780
0"
#790
b111 3
1"
#800
0"
#810
b1000 3
1"
#820
0"
#830
b1001 3
1"
#840
0"
#850
b1010 3
1"
#860
0"
#870
1+
1)
1-
1.
b0 3
1"
#880
0"
#890
0)
0+
1-
b10 4
b10000 <
0.
b1 3
1"
#900
0"
#910
b10 3
1"
#920
0"
#930
b11 3
1"
#940
0"
#950
b100 3
1"
#960
0"
#970
b101 3
1"
#980
0"
#990
b110 3
1"
#1000
0"
#1010
b111 3
1"
#1020
0"
#1030
b1000 3
1"
#1040
0"
#1050
b1001 3
1"
#1060
0"
#1070
b1010 3
1"
#1080
0"
#1090
1+
1)
1-
1.
b0 3
1"
#1100
0"
#1110
0)
0+
1-
0.
b1 3
b1000 <
b11 4
1"
#1120
0"
#1130
b10 3
1"
#1140
0"
#1150
b11 3
1"
#1160
0"
#1170
b100 3
1"
#1180
0"
#1190
b101 3
1"
#1200
0"
#1210
b110 3
1"
#1220
0"
#1230
b111 3
1"
#1240
0"
#1250
b1000 3
1"
#1260
0"
#1270
b1001 3
1"
#1280
0"
#1290
b1010 3
1"
#1300
0"
#1310
1+
1)
1-
1.
b0 3
1"
#1320
0"
#1330
0)
0+
1-
b100 4
b100 <
0.
b1 3
1"
#1340
0"
#1350
b10 3
1"
#1360
0"
#1370
b11 3
1"
#1380
0"
#1390
b100 3
1"
#1400
0"
#1410
b101 3
1"
#1420
0"
#1430
b110 3
1"
#1440
0"
#1450
b111 3
1"
#1460
0"
#1470
b1000 3
1"
#1480
0"
#1490
b1001 3
1"
#1500
0"
#1510
b1010 3
1"
#1520
0"
#1530
1+
1)
1-
1.
b0 3
1"
#1540
0"
#1550
0)
0+
1-
0.
b1 3
b10 <
b101 4
1"
#1560
0"
#1570
b10 3
1"
#1580
0"
#1590
b11 3
1"
#1600
0"
#1610
b100 3
1"
#1620
0"
#1630
b101 3
1"
#1640
0"
#1650
b110 3
1"
#1660
0"
#1670
b111 3
1"
#1680
0"
#1690
b1000 3
1"
#1700
0"
#1710
b1001 3
1"
#1720
0"
#1730
b1010 3
1"
#1740
0"
#1750
1+
1)
1-
1.
b0 3
1"
#1760
0"
#1770
1!
1'
0)
0+
1-
b110 4
b1 <
0.
b1 3
1"
#1780
0"
#1790
b10 3
1"
#1800
0"
#1810
b11 3
1"
#1820
0"
#1830
b100 3
1"
#1840
0"
#1850
b101 3
1"
#1860
0"
#1870
b110 3
1"
#1880
0"
#1890
b111 3
1"
#1900
0"
#1910
b1000 3
1"
#1920
0"
#1930
b1001 3
1"
#1940
0"
#1950
b1010 3
1"
#1960
0"
#1970
1+
1)
1-
1.
b0 3
1"
#1980
0"
#1990
0!
0)
0+
1-
0'
0.
b1 3
b0 <
b111 4
1"
#2000
0"
#2010
b10 3
1"
#2020
0"
#2030
b11 3
1"
#2040
0"
#2050
b100 3
1"
#2060
0"
#2070
b101 3
1"
#2080
0"
#2090
b110 3
1"
#2100
0"
#2110
b111 3
1"
#2120
0"
#2130
b1000 3
1"
#2140
0"
#2150
b1001 3
1"
#2160
0"
#2170
b1010 3
1"
#2180
0"
#2190
1+
1)
1-
1.
b0 3
1"
#2200
0"
#2210
b11 9
0)
0+
1-
1,
b0 4
0.
b1 3
1"
#2220
0"
#2230
1!
1-
b11 (
b11 :
b10 3
0,
1"
#2240
0"
#2250
b11 3
1"
#2260
0"
#2270
b100 3
1"
#2280
0"
#2290
b101 3
1"
#2300
0"
#2310
b110 3
1"
#2320
0"
#2330
b111 3
1"
#2340
0"
#2350
b1000 3
1"
#2360
0"
#2370
b1001 3
1"
#2380
0"
#2390
b1010 3
1"
#2400
0"
#2410
b0 9
1-
1.
b0 3
1"
#2420
0"
#2430
0-
b0 (
b0 :
0.
b1 3
1"
#2440
0"
#2450
b0 3
1"
